{
    "code": 200,
    "data": {
        "level": 10,
        "listenSongs": 32532,
        "userPoint": {
            "userId": 32953014,
            "balance": 294,
            "updateTime": 1702461150384,
            "version": 10,
            "status": 1,
            "blockBalance": 0
        },
        "mobileSign": false,
        "pcSign": false,
        "profile": {
            "privacyItemUnlimit": {
                "area": true,
                "college": true,
                "gender": true,
                "age": true,
                "villageAge": true
            },
            "avatarDetail": null,
            "createTime": 1407747900967,
            "avatarImgId": 109951165601796690,
            "birthday": 1525918298004,
            "gender": 0,
            "nickname": "binaryify",
            "backgroundImgIdStr": "109951163792144631",
            "avatarImgIdStr": "109951165601796681",
            "description": "",
            "userId": 32953014,
            "avatarUrl": "http://p1.music.126.net/axewGX7u9P9Iuqjep-3mmQ==/109951165601796681.jpg",
            "accountStatus": 0,
            "vipType": 11,
            "userType": 0,
            "mutual": false,
            "followed": true,
            "remarkName": null,
            "authStatus": 0,
            "detailDescription": "",
            "experts": {},
            "expertTags": null,
            "djStatus": 10,
            "province": 440000,
            "city": 440300,
            "defaultAvatar": false,
            "backgroundImgId": 109951163792144620,
            "backgroundUrl": "http://p1.music.126.net/WLTBvNL_l9ZKlslFwaCM9Q==/109951163792144631.jpg",
            "signature": "test",
            "authority": 0,
            "followeds": 73,
            "follows": 21,
            "blacklist": false,
            "eventCount": 17,
            "allSubscribedCount": 0,
            "playlistBeSubscribedCount": 4,
            "followTime": "已关注4天",
            "followMe": false,
            "artistIdentity": [],
            "cCount": 0,
            "inBlacklist": false,
            "sDJPCount": 0,
            "playlistCount": 20,
            "sCount": 0,
            "newFollows": 21
        },
        "peopleCanSeeMyPlayRecord": false,
        "bindings": [
            {
                "url": "",
                "expired": false,
                "userId": 32953014,
                "expiresIn": 2147483647,
                "refreshTime": 1592285666,
                "bindingTime": 1426295169224,
                "tokenJsonStr": null,
                "id": 28098251,
                "type": 1
            },
            {
                "url": "http://weibo.com/u/5144142752",
                "expired": true,
                "userId": 32953014,
                "expiresIn": 2628968,
                "refreshTime": 1507142393,
                "bindingTime": 1407747883151,
                "tokenJsonStr": null,
                "id": 18574366,
                "type": 2
            }
        ],
        "adValid": false,
        "code": 200,
        "newUser": false,
        "recallUser": false,
        "createTime": 1407747900967,
        "createDays": 3412,
        "profileVillageInfo": {
            "title": "领取村民证",
            "imageUrl": null,
            "targetUrl": "https://sg.music.163.com/g/cloud-card-2?nm_style=sbt&market=personal"
        }
    }
}